chatifier/__init__.py
chatifier/__main__.py
chatifier/cli.py
chatifier/clients.py
chatifier/detector.py
chatifier/ui.py
chatifier/utils.py
llm_chatifier-0.2.3.dist-info/METADATA
llm_chatifier-0.2.3.dist-info/WHEEL
llm_chatifier-0.2.3.dist-info/entry_points.txt
llm_chatifier-0.2.3.dist-info/top_level.txt
llm_chatifier-0.2.3.dist-info/RECORD
