Metadata-Version: 2.4
Name: llm-chatifier
Version: 0.2.3
Summary: A universal terminal chat client that auto-detects and connects to any chat API endpoint
License: BSD-3-Clause
Requires-Python: >=3.8
Requires-Dist: click>=8.0.0
Requires-Dist: httpx>=0.24.0
Requires-Dist: rich>=13.0.0
Requires-Dist: prompt-toolkit>=3.0.0
